flashback/__init__.py
flashback/accessing/__init__.py
flashback/accessing/dig.py
flashback/accessing/pick.py
flashback/accessing/values_at.py
flashback/borg.py
flashback/caching/__init__.py
flashback/caching/adapters/__init__.py
flashback/caching/adapters/base.py
flashback/caching/adapters/disk_adapter.py
flashback/caching/adapters/memcached_adapter.py
flashback/caching/adapters/memory_adapter.py
flashback/caching/adapters/redis_adapter.py
flashback/caching/cache.py
flashback/caching/cached.py
flashback/classproperty.py
flashback/debugging/__init__.py
flashback/debugging/caller.py
flashback/debugging/filters/__init__.py
flashback/debugging/filters/call_highlight_filter.py
flashback/debugging/filters/decorator_operator_filter.py
flashback/debugging/filters/type_highlight_filter.py
flashback/debugging/formatter.py
flashback/debugging/get_call_context.py
flashback/debugging/get_callable.py
flashback/debugging/get_frameinfo.py
flashback/debugging/parser.py
flashback/debugging/profiled.py
flashback/debugging/styles/__init__.py
flashback/debugging/styles/jellybeans.py
flashback/debugging/xp.py
flashback/deprecated.py
flashback/encrypted_file.py
flashback/formatting/__init__.py
flashback/formatting/_inflect.py
flashback/formatting/adverbize.py
flashback/formatting/camelize.py
flashback/formatting/kebabize.py
flashback/formatting/locales/__init__.py
flashback/formatting/locales/de.py
flashback/formatting/locales/en.py
flashback/formatting/locales/es.py
flashback/formatting/locales/fr.py
flashback/formatting/ordinalize.py
flashback/formatting/oxford_join.py
flashback/formatting/parameterize.py
flashback/formatting/pascalize.py
flashback/formatting/pluralize.py
flashback/formatting/singularize.py
flashback/formatting/snakeize.py
flashback/formatting/transliterate.py
flashback/formatting/truncate.py
flashback/i16g/__init__.py
flashback/i16g/locale.py
flashback/importing/__init__.py
flashback/importing/import_class_from_path.py
flashback/importing/import_module_from_path.py
flashback-3.1.5.dist-info/licenses/LICENSE
flashback-3.1.5.dist-info/WHEEL
flashback-3.1.5.dist-info/METADATA
flashback-3.1.5.dist-info/RECORD
