Metadata-Version: 2.4
Name: flashback
Version: 3.1.5
Summary: A collection of python utilities you might have written a couple of times already
Author: Paul Renvoisé
Author-email: Paul Renvoisé <renvoisepaul@gmail.com>
License-File: LICENSE
Classifier: Development Status :: 5 - Production/Stable
Classifier: Environment :: Console
Classifier: Intended Audience :: Developers
Classifier: Operating System :: Unix
Classifier: Programming Language :: Python
Classifier: Programming Language :: Python :: 3.12
Classifier: Programming Language :: Python :: 3.13
Classifier: Programming Language :: Python :: 3.14
Classifier: Programming Language :: Python :: 3 :: Only
Classifier: Programming Language :: Python :: Implementation :: CPython
Classifier: Topic :: Software Development :: Libraries :: Python Modules
Classifier: Topic :: Utilities
Requires-Dist: cryptography>=46.0.3,<47.0.0
Requires-Dist: pygments>=2.19.0,<3.0.0
Requires-Dist: pymemcache>=3.5.0,<4.0.0
Requires-Dist: redis>=5.3.0,<6.0.0
Requires-Dist: regex>=2025.11.0,<2025.12.0
Requires-Dist: unidecode>=1.3.0,<2.0.0
Requires-Python: >=3.12
Project-URL: homepage, https://github.com/PaulRenvoise/flashback
Project-URL: repository, https://github.com/PaulRenvoise/flashback
